kv/rest/__init__.py
kv/rest/__init__.pyi
kv/rest/cli.py
kv/rest/client.py
kv/rest/clientgen_cli.py
kv/rest/request.py
kv/rest/server.py
kv_rest-0.1.11.dist-info/METADATA
kv_rest-0.1.11.dist-info/WHEEL
kv_rest-0.1.11.dist-info/entry_points.txt
kv_rest-0.1.11.dist-info/top_level.txt
kv_rest-0.1.11.dist-info/RECORD
