Metadata-Version: 2.1
Name: kv-rest
Version: 0.1.11
Summary: Rest API and client for a server-side KV
Author-email: Marcel Claramunt <marcel@moveread.com>
Project-URL: repo, https://github.com/marciclabas/python-storage.git
Requires-Python: >=3.10
Requires-Dist: kv-api
Requires-Dist: pydantic
Requires-Dist: haskellian
Provides-Extra: cli
Requires-Dist: dslog ; extra == 'cli'
Requires-Dist: uvicorn[standard] ; extra == 'cli'
Provides-Extra: client
Requires-Dist: httpx ; extra == 'client'
Provides-Extra: fs
Requires-Dist: kv-fs ; extra == 'fs'
Provides-Extra: server
Requires-Dist: fastapi ; extra == 'server'
Requires-Dist: python-multipart ; extra == 'server'
Provides-Extra: sqlite
Requires-Dist: kv-sqlite-sync ; extra == 'sqlite'
